LICENSE.md
MANIFEST.in
README.rst
setup.py
ovp_core/__init__.py
ovp_core/apps.py
ovp_core/emails.py
ovp_core/urls.py
ovp_core/validators.py
ovp_core/views.py
ovp_core.egg-info/PKG-INFO
ovp_core.egg-info/SOURCES.txt
ovp_core.egg-info/dependency_links.txt
ovp_core.egg-info/not-zip-safe
ovp_core.egg-info/requires.txt
ovp_core.egg-info/top_level.txt
ovp_core/__pycache__/__init__.cpython-35.pyc
ovp_core/__pycache__/apps.cpython-35.pyc
ovp_core/__pycache__/emails.cpython-35.pyc
ovp_core/__pycache__/helpers.cpython-35.pyc
ovp_core/__pycache__/urls.cpython-35.pyc
ovp_core/__pycache__/validators.cpython-35.pyc
ovp_core/__pycache__/views.cpython-35.pyc
ovp_core/admin/__init__.py
ovp_core/admin/address.py
ovp_core/admin/cause.py
ovp_core/admin/lead.py
ovp_core/admin/skill.py
ovp_core/admin/__pycache__/__init__.cpython-35.pyc
ovp_core/admin/__pycache__/address.cpython-35.pyc
ovp_core/admin/__pycache__/cause.cpython-35.pyc
ovp_core/admin/__pycache__/lead.cpython-35.pyc
ovp_core/admin/__pycache__/skill.cpython-35.pyc
ovp_core/helpers/__init__.py
ovp_core/helpers/csv.py
ovp_core/helpers/xls.py
ovp_core/helpers/__pycache__/__init__.cpython-35.pyc
ovp_core/helpers/__pycache__/csv.cpython-35.pyc
ovp_core/helpers/__pycache__/xls.cpython-35.pyc
ovp_core/locale/pt_BR/LC_MESSAGES/django.mo
ovp_core/locale/pt_BR/LC_MESSAGES/django.po
ovp_core/migrations/0001_initial.py
ovp_core/migrations/0002_auto_20161019_1557.py
ovp_core/migrations/0003_cause_skill.py
ovp_core/migrations/0004_load_skills_and_causes.py
ovp_core/migrations/0005_auto_20170111_1633.py
ovp_core/migrations/0005_auto_20170112_1417.py
ovp_core/migrations/0006_merge_20170112_2144.py
ovp_core/migrations/0007_lead.py
ovp_core/migrations/0008_availability.py
ovp_core/migrations/0009_cause_image.py
ovp_core/migrations/0009_lead_date.py
ovp_core/migrations/0010_merge_20170609_1453.py
ovp_core/migrations/0011_simpleaddress.py
ovp_core/migrations/0012_simpleaddress_supplement.py
ovp_core/migrations/__init__.py
ovp_core/migrations/__pycache__/0001_initial.cpython-35.pyc
ovp_core/migrations/__pycache__/0002_auto_20161019_1557.cpython-35.pyc
ovp_core/migrations/__pycache__/0003_cause_skill.cpython-35.pyc
