Metadata-Version: 1.1
Name: ovp-core
Version: 1.2.6
Summary: This module has core functionality for ovp projects, such as creation, editing and retrieving.
Home-page: https://github.com/OpenVolunteeringPlatform/django-ovp-core
Author: Atados
Author-email: arroyo@atados.com.br
License: AGPL
Download-URL: https://github.com/OpenVolunteeringPlatform/django-ovp-core/tarball/1.2.4
Platform: UNKNOWN
